{
  "metadata": {
    "type": "class_arguments",
    "class_name": "RegularBoundMatrix",
    "description": "NKM HLW CORE"
  },
  "arguments": {
    "factory": "geo",
    "transform_data": [[-161, -169, 0]],
    "nxi": 14,
    "nyj": 13,
    "nzk": 35,
    "dxi": 23,
    "dyj": 26,
    "dzk": 2.11,
    "dx0": 0,
    "dy0": 0,
    "dz0": 35.575,
    "dx1": 0,
    "dy1": 0,
    "dz1": 35.575,
    "x0_y0_z0": null,
    "xi_y0_z0": null,
    "x1_y0_z0": null,
    "x0_yj_z0": null,
    "xi_yj_z0": ["input/nkm_03_2020_xiyjz0_hlw_mix_lres.json", 3],
    "x1_yj_z0": null,
    "x0_y1_z0": null,
    "xi_y1_z0": null,
    "x1_y1_z0": null,
    "x0_y0_zk": null,
    "xi_y0_zk": null,
    "x1_y0_zk": null,
    "x0_yj_zk": null,
    "xi_yj_zk": ["input/nkm_03_2020_xiyjzk_hlw_lres.json", 3],
    "x1_yj_zk": null,
    "x0_y1_zk": null,
    "xi_y1_zk": null,
    "x1_y1_zk": null,
    "x0_y0_z1": null,
    "xi_y0_z1": null,
    "x1_y0_z1": null,
    "x0_yj_z1": null,
    "xi_yj_z1": ["input/nkm_03_2020_xiyjz1_hlw_mix_lres.json", 3],
    "x1_yj_z1": null,
    "x0_y1_z1": null,
    "xi_y1_z1": null,
    "x1_y1_z1": null
  }
}